mrx_link_core/__init__.py
mrx_link_core/_version.py
mrx_link_core/callbacks/__init__.py
mrx_link_core/callbacks/pipeline_info.cp39-win_amd64.pyd
mrx_link_core/capture/__init__.py
mrx_link_core/capture/capture_manager.cp39-win_amd64.pyd
mrx_link_core/capture/captured_io.cp39-win_amd64.pyd
mrx_link_core/common/__init__.py
mrx_link_core/common/info.cp39-win_amd64.pyd
mrx_link_core/common/mixins.cp39-win_amd64.pyd
mrx_link_core/common/pickler.cp39-win_amd64.pyd
mrx_link_core/common/utils.cp39-win_amd64.pyd
mrx_link_core/components/__init__.py
mrx_link_core/components/code_cell.cp39-win_amd64.pyd
mrx_link_core/contrib/__init__.py
mrx_link_core/contrib/diskcache/__init__.py
mrx_link_core/contrib/diskcache/cli.cp39-win_amd64.pyd
mrx_link_core/contrib/diskcache/core.cp39-win_amd64.pyd
mrx_link_core/contrib/diskcache/djangocache.cp39-win_amd64.pyd
mrx_link_core/contrib/diskcache/fanout.cp39-win_amd64.pyd
mrx_link_core/contrib/diskcache/persistent.cp39-win_amd64.pyd
mrx_link_core/contrib/diskcache/recipes.cp39-win_amd64.pyd
mrx_link_core/executors/__init__.py
mrx_link_core/executors/utils.cp39-win_amd64.pyd
mrx_link_core/executors/component_executor/__init__.py
mrx_link_core/executors/component_executor/execute_functions.cp39-win_amd64.pyd
mrx_link_core/executors/remote_executor/__init__.py
mrx_link_core/executors/remote_executor/__main__.py
mrx_link_core/executors/remote_executor/executor.cp39-win_amd64.pyd
mrx_link_core/executors/remote_executor/tasks.cp39-win_amd64.pyd
mrx_link_core/ipython/__init__.py
mrx_link_core/ipython/display_router.cp39-win_amd64.pyd
mrx_link_core/ipython/kernelapp.cp39-win_amd64.pyd
mrx_link_core/ipython/terminalapp.cp39-win_amd64.pyd
mrx_link_core/ipython/utils.cp39-win_amd64.pyd
mrx_link_core/misc/__init__.py
mrx_link_core/misc/error.cp39-win_amd64.pyd
mrx_link_core/misc/enums/__init__.py
mrx_link_core/misc/enums/component_status.cp39-win_amd64.pyd
mrx_link_core/misc/enums/dag_exec.cp39-win_amd64.pyd
mrx_link_core-2.3.1.dist-info/METADATA
mrx_link_core-2.3.1.dist-info/WHEEL
mrx_link_core-2.3.1.dist-info/top_level.txt
mrx_link_core-2.3.1.dist-info/RECORD
